<annotation>
        <folder>images</folder>
        <filename>014169492.jpg</filename>
        <path>../../videos/images/014169492.jpg</path>
        <source>
                <database>Unknown</database>
        </source>
        <size>
                <width>634</width>
                <height>356</height>
                <depth>3</depth>
        </size>
        <segmented>0</segmented>
        <object>
                <name>stay</name>
                <pose>Unspecified</pose>
                <truncated>0</truncated>
                <difficult>0</difficult>
                <bndbox>
                        <xmin>352</xmin>
                        <ymin>61</ymin>
                        <xmax>433</xmax>
                        <ymax>258</ymax>
                </bndbox>
        </object>
        <object>
                <name>walk</name>
                <pose>Unspecified</pose>
                <truncated>0</truncated>
                <difficult>0</difficult>
                <bndbox>
                        <xmin>352</xmin>
                        <ymin>61</ymin>
                        <xmax>433</xmax>
                        <ymax>258</ymax>
                </bndbox>
        </object>
</annotation>