<annotation>
        <folder>images</folder>
        <filename>017930226.jpg</filename>
        <path>../../videos/images/017930226.jpg</path>
        <source>
                <database>Unknown</database>
        </source>
        <size>
                <width>634</width>
                <height>356</height>
                <depth>3</depth>
        </size>
        <segmented>0</segmented>
        <object>
                <name>walk</name>
                <pose>Unspecified</pose>
                <truncated>0</truncated>
                <difficult>0</difficult>
                <bndbox>
                        <xmin>118</xmin>
                        <ymin>267</ymin>
                        <xmax>164</xmax>
                        <ymax>356</ymax>
                </bndbox>
        </object>
        <object>
                <name>stay</name>
                <pose>Unspecified</pose>
                <truncated>0</truncated>
                <difficult>0</difficult>
                <bndbox>
                        <xmin>435</xmin>
                        <ymin>253</ymin>
                        <xmax>500</xmax>
                        <ymax>375</ymax>
                </bndbox>
        </object>
        <object>
                <name>stay</name>
                <pose>Unspecified</pose>
                <truncated>0</truncated>
                <difficult>0</difficult>
                <bndbox>
                        <xmin>14</xmin>
                        <ymin>274</ymin>
                        <xmax>79</xmax>
                        <ymax>354</ymax>
                </bndbox>
        </object>
</annotation>