<annotation>
        <folder>generated</folder>
        <filename>schladming_4030.jpg</filename>
        <path>screenshots/schladming_4030.jpg</path>
        <source>
                <database>Unknown</database>
        </source>
        <size>
                <width>960</width>
                <height>540</height>
                <depth>3</depth>
        </size>
        <segmented>0</segmented>
        <object>
            <name>goesser</name>
            <pose>Unspecified</pose>
            <truncated>0</truncated>
            <difficult>0</difficult>
            <bndbox>
                    <xmin>258</xmin>
                    <ymin>394</ymin>
                    <xmax>400</xmax>
                    <ymax>481</ymax>
            </bndbox>
    </object>
        <object>
            <name>steiermark</name>
            <pose>Unspecified</pose>
            <truncated>0</truncated>
            <difficult>0</difficult>
            <bndbox>
                    <xmin>905</xmin>
                    <ymin>488</ymin>
                    <xmax>931</xmax>
                    <ymax>507</ymax>
            </bndbox>
    </object>
        <object>
            <name>steiermark</name>
            <pose>Unspecified</pose>
            <truncated>0</truncated>
            <difficult>0</difficult>
            <bndbox>
                    <xmin>60</xmin>
                    <ymin>512</ymin>
                    <xmax>98</xmax>
                    <ymax>539</ymax>
            </bndbox>
    </object>
        <object>
            <name>kronenzeitung</name>
            <pose>Unspecified</pose>
            <truncated>0</truncated>
            <difficult>0</difficult>
            <bndbox>
                    <xmin>139</xmin>
                    <ymin>416</ymin>
                    <xmax>243</xmax>
                    <ymax>491</ymax>
            </bndbox>
    </object>
</annotation>