<annotation>
        <folder>generated</folder>
        <filename>schladming_40030.jpg</filename>
        <path>screenshots/schladming_40030.jpg</path>
        <source>
                <database>Unknown</database>
        </source>
        <size>
                <width>960</width>
                <height>540</height>
                <depth>3</depth>
        </size>
        <segmented>0</segmented>
        <object>
            <name>goesser</name>
            <pose>Unspecified</pose>
            <truncated>0</truncated>
            <difficult>0</difficult>
            <bndbox>
                    <xmin>873</xmin>
                    <ymin>136</ymin>
                    <xmax>959</xmax>
                    <ymax>209</ymax>
            </bndbox>
    </object>
</annotation>